moneyonchain/__init__.py
moneyonchain/account.py
moneyonchain/accounts.py
moneyonchain/chain.py
moneyonchain/changers.py
moneyonchain/config.json
moneyonchain/contract.py
moneyonchain/events.py
moneyonchain/history.py
moneyonchain/main.py
moneyonchain/network_manager.py
moneyonchain/networks.json
moneyonchain/networks.py
moneyonchain/rpc.py
moneyonchain/transaction.py
moneyonchain/utils.py
moneyonchain/fastbtc/__init__.py
moneyonchain/fastbtc/events.py
moneyonchain/fastbtc/fastbtcbridge.py
moneyonchain/fastbtc/abi/FastBtcBridge.abi
moneyonchain/fastbtc/abi/FastBtcBridge.bin
moneyonchain/governance/__init__.py
moneyonchain/governance/admin.py
moneyonchain/governance/changers.py
moneyonchain/governance/governed.py
moneyonchain/governance/governor.py
moneyonchain/governance/stopper.py
moneyonchain/governance/abi/AdminUpgradeabilityProxy.abi
moneyonchain/governance/abi/AdminUpgradeabilityProxy.bin
moneyonchain/governance/abi/BatchChanger.abi
moneyonchain/governance/abi/BatchChanger.bin
moneyonchain/governance/abi/BlockableGovernor.abi
moneyonchain/governance/abi/BlockableGovernor.bin
moneyonchain/governance/abi/Governed.abi
moneyonchain/governance/abi/Governed.bin
moneyonchain/governance/abi/Governor.abi
moneyonchain/governance/abi/Governor.bin
moneyonchain/governance/abi/MoCIGovernorChanger.abi
moneyonchain/governance/abi/MoCIGovernorChanger.bin
moneyonchain/governance/abi/ProxyAdmin.abi
moneyonchain/governance/abi/ProxyAdmin.bin
moneyonchain/governance/abi/ProxyAdminIGovernorChanger.abi
moneyonchain/governance/abi/ProxyAdminIGovernorChanger.bin
moneyonchain/governance/abi/SkipVotingProcessChange.abi
moneyonchain/governance/abi/SkipVotingProcessChange.bin
moneyonchain/governance/abi/Stoppable.abi
moneyonchain/governance/abi/Stoppable.bin
moneyonchain/governance/abi/Stopper.abi
moneyonchain/governance/abi/Stopper.bin
moneyonchain/governance/abi/UpgradeDelegator.abi
moneyonchain/governance/abi/UpgradeDelegator.bin
moneyonchain-2.1.22.dist-info/LICENSE
moneyonchain-2.1.22.dist-info/METADATA
moneyonchain-2.1.22.dist-info/WHEEL
moneyonchain-2.1.22.dist-info/top_level.txt
moneyonchain-2.1.22.dist-info/RECORD
